mozilla_nimbus_shared/__init__.py
mozilla_nimbus_shared/data.json
mozilla_nimbus_shared/schemas/experiments/NimbusExperiment.json
mozilla_nimbus_shared/schemas/features/Feature.json
mozilla_nimbus_shared/schemas/messaging/SimpleCFRMessage.json
mozilla_nimbus_shared/schemas/messaging/SpecialMessageActionSchemas.json
mozilla_nimbus_shared/schemas/messaging/TriggerActionSchemas.json
mozilla_nimbus_shared/schemas/normandy/AddonRollbackArguments.json
mozilla_nimbus_shared/schemas/normandy/AddonRolloutArguments.json
mozilla_nimbus_shared/schemas/normandy/BranchedAddonStudyArguments.json
mozilla_nimbus_shared/schemas/normandy/ConsoleLogArguments.json
mozilla_nimbus_shared/schemas/normandy/MessagingExperimentArguments.json
mozilla_nimbus_shared/schemas/normandy/MultiPreferenceExperimentArguments.json
mozilla_nimbus_shared/schemas/normandy/NormandyRecipe.json
mozilla_nimbus_shared/schemas/normandy/OptOutStudyArguments.json
mozilla_nimbus_shared/schemas/normandy/PreferenceExperimentArguments.json
mozilla_nimbus_shared/schemas/normandy/PreferenceRollbackArguments.json
mozilla_nimbus_shared/schemas/normandy/PreferenceRolloutArguments.json
mozilla_nimbus_shared/schemas/normandy/ShowHeartbeatArguments.json
mozilla_nimbus_shared/schemas/schemas/experiments/NimbusExperiment.json
mozilla_nimbus_shared/schemas/schemas/features/Feature.json
mozilla_nimbus_shared/schemas/schemas/normandy/AddonRollbackArguments.json
mozilla_nimbus_shared/schemas/schemas/normandy/AddonRolloutArguments.json
mozilla_nimbus_shared/schemas/schemas/normandy/BranchedAddonStudyArguments.json
mozilla_nimbus_shared/schemas/schemas/normandy/ConsoleLogArguments.json
mozilla_nimbus_shared/schemas/schemas/normandy/MessagingExperimentArguments.json
mozilla_nimbus_shared/schemas/schemas/normandy/MultiPreferenceExperimentArguments.json
mozilla_nimbus_shared/schemas/schemas/normandy/NormandyRecipe.json
mozilla_nimbus_shared/schemas/schemas/normandy/OptOutStudyArguments.json
mozilla_nimbus_shared-2.5.2.dist-info/WHEEL
mozilla_nimbus_shared-2.5.2.dist-info/METADATA
mozilla_nimbus_shared-2.5.2.dist-info/RECORD
