Metadata-Version: 2.1
Name: mozilla-nimbus-shared
Version: 2.5.2
Summary: Shared data and schemas for Project Nimbus
License: MPL-2.0
Author: Michael Cooper
Author-email: mcooper@mozilla.com
Requires-Python: >=3.7,<4.0
Classifier: License :: OSI Approved
Classifier: Programming Language :: Python :: 3
Classifier: Programming Language :: Python :: 3.7
Classifier: Programming Language :: Python :: 3.8
Classifier: Programming Language :: Python :: 3.9
Classifier: Programming Language :: Python :: 3.10
Classifier: Programming Language :: Python :: 3.11
Requires-Dist: jsonschema (>=4.17.3,<5.0.0)
